{
  "documents_processed": 1816,
  "documents_with_headers": 1440,
  "header_counts": {
    "CONCLUSION": 597,
    "NOTICE OF DECISION": 734,
    "INTRODUCTION": 212,
    "ALLEGATIONS": 72,
    "DECISION": 251,
    "ANALYSIS": 525,
    "REMOVAL ORDER": 246,
    "ORAL REASONS FOR DECISION": 52,
    "PIF.": 2,
    "DETERMINATION": 258,
    "REASONS FOR DECISION": 669,
    "EXPRESS STATUTORY CONDITIONS": 4,
    "NEWNESS": 1,
    "CREDIBILITY": 8,
    "RELEVANCE": 1,
    "MATERIALITY": 1,
    "ROLE OF THE RAD": 51,
    "FURTHER RAD FINDINGS": 1,
    "RESIDENCY OBLIGATION": 211,
    "BACKGROUND": 306,
    "RAD DETERMINATION": 1,
    "ADMISSIBILITY OF EVIDENCE SUBMITTED ON APPEAL": 7,
    "NO ORAL HEARING": 7,
    "ISSUES IN APPEAL": 24,
    "RAD ANALYSIS": 5,
    "OVERVIEW": 123,
    "ISSUES ON APPEAL": 1,
    "SOGIE.": 1,
    "SPONSORSHIP": 174,
    "PARTNERSHIP APPEAL": 1,
    "AUTHORIZATION TO RETURN TO CANADA": 1,
    "NOTICE OF DEC ISION": 2,
    "CONC LUSION": 5,
    "REASONS AND DECISION": 3,
    "ISSUE": 123,
    "REASONS FO R DECISION": 1,
    "RECONSIDERATION": 1,
    "REMOVAL O RDER": 1,
    "ISSUE AND DECISION": 10,
    "THE LAW": 3,
    "ANALYSIS AND FINDINGS OF FA CT": 1,
    "ANAL YSIS AND FINDINGS OF FACT": 1,
    "NOTICE  OF DECISION": 5,
    "DE CISION": 4,
    "CON CLUSION": 4,
    "CONCLUSIO N": 8,
    "NOTICE OF DECI SION": 2,
    "BACKGR OUND": 3,
    "DECISIO N": 2,
    "PRELIMINARY MATTER": 1,
    "INTRODUCTION AND ISSUE": 3,
    "IRPA .": 11,
    "CONCLUS ION": 5,
    "CONTEXT": 3,
    "DISPOSITION AND REMEDY": 4,
    "ROL E OF THE RAD": 1,
    "RE ASONS FOR DECISION": 1,
    "REASONS FOR DE CISION": 3,
    "SUBMISSIONS BY THE APPELLANT": 3,
    "SUMMARY": 8,
    "DISPOSITION": 30,
    "REASONS FOR DECISI ON": 3,
    "U.S.": 2,
    "IRPA": 1,
    "MERITS OF THE APPEAL": 10,
    "ISSUE AND LAW": 2,
    "ANALYSIS AND FINDING S OF FACT": 3,
    "RELEVANT LAW": 4,
    "ANALYTICAL FRAMEWORK": 1,
    "FINDING OF FACT AND ANALYSIS": 2,
    "MINISTERIAL INTERVENTION AT THE RPD": 1,
    "ROLE OF RAD": 3,
    "SUBMISSIONS BY COUNSEL": 2,
    "ORAL HEARING": 2,
    "DETERMINATION - XXXX XXXX": 1,
    "UKRAINE": 1,
    "DETERMINATION OF THE APPEAL": 30,
    "SUBMISSIONS BY MINISTER": 1,
    "SUBMISSIONS": 10,
    "SUBMISSIONS BY RESPONDENT": 1,
    "RAD.": 5,
    "GUY104576.E.": 1,
    "DETE RMINATION": 1,
    "IRPA.": 10,
    "PRELIMINARY MATTERS": 3,
    "THE LEGISLATION AND OTHER MATERIALS CONSIDERED": 1,
    "THRESHOLD JURISDICTIONAL ISSUE": 1,
    "ISSUES": 39,
    "REMOVAL": 5,
    "BACKGROU ND": 3,
    "NOTICE OF DECISI ON": 1,
    "HEARING": 24,
    "COMMENT ON EVIDENCE": 1,
    "SUBMISSIONS BY THE APP ELLANT": 1,
    "NEW EVIDENCE": 7,
    "DISPOSSITION": 1,
    "DETERMINAT ION": 3,
    "COUNTRY  ENTRY": 1,
    "OF DAYS": 1,
    "USA  15-06-2014  19-06-2014  05": 1,
    "TAX YEAR  INCOME": 1,
    "DECLARED  TAX OWED  REFUND OR": 1,
    "UAE.": 2,
    "REMEDY SOUGHT": 1,
    "RAD:4": 1,
    "A. WAR  REFUGEES": 1,
    "ANALYS IS": 32,
    "DETERMINATIO N": 2,
    "SUMMARY AND DETERMINATION": 2,
    "REASONS  FOR DECISION": 3,
    "ADMISSIBILITY OF EVIDENCE PRESENTED ON APPEAL": 1,
    "SERVICE OF DOCUMENTS": 1,
    "DOCUMENT SUBMITTED ON APPEAL": 1,
    "DETERMINATION OF THE AP PEAL": 1,
    "CONCLUSI ON": 2,
    "ISSUE  AND LAW": 3,
    "PROCEDURAL HISTORY": 2,
    "ANALYSIS OF EXCLUSION ISSUE": 1,
    "DETERMINATION S": 1,
    "NO NEW EVIDENCE OR ORAL HEARING": 8,
    "RPD DECISION": 1,
    "REQUEST FOR A HEARING": 1,
    "APPLICABLE LEGAL PRINCIPLES": 1,
    "RESIDENT STATUS": 1,
    "JAIRAM MAHARAJ": 1,
    "JASMIN MAHARAJ": 1,
    "IAD .": 1,
    "LEGISLATION": 2,
    "DETERMIN ATIVE ISSUES": 1,
    "SCOPE OF THE APPEAL": 5,
    "I. INTRODUCTION": 10,
    "II. BACKGROUND": 9,
    "IV.  DETERMINATIVE ISSUE": 2,
    "V.  SCOPE OF THE RAD APPEAL": 2,
    "VI.  ANALYSIS": 2,
    "VII.  REMEDY": 4,
    "LEGAL VALIDITY": 8,
    "IMMIGRATION AND REFUGEE BOARD": 5,
    "TB 7-18394                           5969 -6878": 7,
    "AYTUG CELIKBAS": 1,
    "IDIL CELIKBUS": 1,
    "DETERMINATIONS": 2,
    "BACKGROUND  AND OVERVIEW OF THE APPEAL": 1,
    "ISSUES  IN APPEAL": 1,
    "ANALYSIS OF FACTORS": 3,
    "SCOPE OF THE RAD REVIEW": 2,
    "BACKGROUND AND OVERV IEW OF APPEAL": 1,
    "US.": 1,
    "BHAVESHKUMAR S XXXXXXXXXXXXXX": 1,
    "GENUINENESS OF THE MARRIAGE": 1,
    "SECOND GROUND OF REFUSAL": 1,
    "FINANCIAL INADMISSIBILITY": 1,
    "HUMANITARIAN AND COMPASSIONATE GROUNDS": 5,
    "CONCLUSION  ON THE APPEAL": 1,
    "GURCHARAN SINGH DANG": 1,
    "JASPAL KAUR DANG": 1,
    "ROLE OF THE REFUGEE APPEAL DIVISION": 2,
    "STATE PROTECTION AND INTERNAL FLIGHT ALTERNATIVE": 2,
    "SCOPE OF RAD REVIEW": 1,
    "REMEDY": 2,
    "BACKGROUND AND ALLEGATIONS": 3,
    "DE TERMINATION": 4,
    "HTI106117.FE.": 1,
    "NEW EVIDENCE AND ORAL HEARING": 2,
    "SCOPE OF RAD APPEAL": 2,
    "REMEDIES": 2,
    "XXXX  2018.": 1,
    "III.  DETERMINATIVE ISSUE": 6,
    "IV. SCOPE OF THE RAD APPEAL": 3,
    "V.  ANALYSI S": 4,
    "VI.  REMEDY": 5,
    "BACKGROUND OF THE CLAIM": 1,
    "RPD FINDINGS": 2,
    "ISSUES RAISED BY THE APPELLANTS": 1,
    "NNEKA GRACE NNODU": 1,
    "DECISION AND DETERMINATIVE ISSUE": 1,
    "ROLE OF THE  RAD": 2,
    "AMENDED": 11,
    "III.  DET ERMINATIVE ISSUE": 1,
    "RPD:": 1,
    "DETERMINATIVE ISSUE": 2,
    "ORAL HEARING BEFORE THE RAD": 1,
    "SCOPE OF THE RAD APPEAL": 1,
    "ZZZ106114.E.": 1,
    "AMENDED VERSION": 1,
    "REMOVAL ORDER APPEA L": 2,
    "IN CAMERA": 2,
    "THE MISREPRESENTATIONS": 1,
    "REMORSE": 1,
    "DEGREE OF ESTABLISHM ENT": 1,
    "INTERESTS OF THE CHI LDREN": 1,
    "NATIONALITY": 1,
    "DECIS ION": 5,
    "IV.  SCOPE OF THE RAD APPEAL": 2,
    "V. ANALYSIS": 4,
    "CO NCLUSION": 2,
    "INTRODUCTION AND DECISION": 1,
    "BA CKGROUND": 2,
    "THE FACTS": 1,
    "OVERVIEW OF APPEAL": 1,
    "RESIDENCY OBLIGATION  APPEAL": 3,
    "REASONS FOR DECISIO N": 5,
    "DETERMINATION OF THE  APPEAL": 2,
    "OSAMAGBE HAPPYMAN OSUND E": 1,
    "LEGAL VALIDITY - MISREPRESENTATION": 1,
    "ANALYSIS - SPECIAL RELIEF": 1,
    "BAC KGROUND": 2,
    "ALI  MOUTTAKI": 1,
    "RKIA  AZIZ  EL  IDRISSI": 1,
    "DICRETIONARY REL IEF": 1,
    "EVIDENCE": 5,
    "THE ROLE OF THE RAD": 3,
    "EVIDENCE AND ANALYSIS": 1,
    "ADMISSIBILITY OF NEW EVI DENCE": 1,
    "DETERMINATIVE ISSUES": 3,
    "MEHRNOOSH ATTAR": 1,
    "RULE 29 APPLICATION": 1,
    "NO ORAL HEAR ING": 1,
    "PSB.": 1,
    "REASON S AND DECISION": 1,
    "II. BACKGROUND  AND OVERVIEW": 2,
    "VI.   REMEDY": 1,
    "NOTICE OF DE CISION": 5,
    "OVERVIEW AND ISSUE": 1,
    "NOTI CE  OF DECISION": 1,
    "V.  ANALYSIS": 1,
    "RESIDENCY OBLIGATION APPEAL": 6,
    "REMOVAL ORDER APPEAL": 9,
    "SPONSORSHIP APPEAL": 8,
    "ANALYSI S": 3,
    "IV.  SCOPE OF THE APPEAL": 1,
    "CHAO YI CHEN": 1,
    "CONCLUSION ON LEGAL VALIDITY": 1,
    "DETERMINATION OF THE APPLICATION": 5,
    "DECI SION": 2,
    "RESIDENCY O BLIGATION": 1,
    "OVERVIEW OF THE APPE AL": 1,
    "SCOPE OF THE APPE AL": 1,
    "FINDINGS OF THE RPD": 1,
    "REQUEST FOR AN ORAL HEARING": 1,
    "GROUNDS FOR APPEAL": 1,
    "CONCLU SION": 1,
    "MINOR APPELLANTS": 1,
    "BACKGROUND AND OVERVIEW OF APPEAL": 1,
    "BOC.": 2,
    "III.  DETERM INATIVE ISSUE": 1,
    "XXXX  2019.": 1,
    "DECISI ON": 3,
    "CONCL USION": 1,
    "REASONS FOR  DECISION": 2,
    "FGM.": 1,
    "DETERMIN ATION": 1,
    "RPD.": 5,
    "RPD DETERMINATION": 1,
    "NEW EVIDENCE AND HEARING": 1,
    "FCA 96. .": 1,
    "APPLICATION TO SUBMIT AD DITIONAL EVIDENCE": 1,
    "CONSIDERATION OF NEW  EVIDENCE": 1,
    "APPLICATION FOR AN O RAL HEARING": 2,
    "LAW": 12,
    "HUMANITARIAN AND COM PASSIONATE GROUNDS": 6,
    "CONFIDENTIAL INFORMATION": 1,
    "XXXXXXXXX MOHAMED KHALIL  RADWAN": 1,
    "IMPORTANT NOTICE REGARDING COUNSEL AND DOCUMENTS": 1,
    "THAT MAY SUPPORT YOUR CLAIM": 1,
    "TC0 04659": 1,
    "ANAL YSIS": 1,
    "THE ISSUES": 1,
    "AMEND ED": 1,
    "RE -OPENING APPLICATION": 1,
    "PRIVATE PROCEEDING": 1,
    "AISSF.": 2,
    "PRIVATE PROCEEDING CONFIDENTIAL FILE": 1,
    "RPD .": 1,
    "FINDINGS OF FACT": 1,
    "COUNTRY CONDI TIONS": 1,
    "THE ISSUE TO BE DETERMINED": 1,
    "BACKGROUND3": 3,
    "PROFIL E": 1,
    "REASONS AND  DECISION": 10,
    "DETERMINATI ON": 1,
    "JURISDICTION": 3,
    "DE NOVO": 2,
    "ANALYSIS OF THE EVIDENCE": 2,
    "NOTICE OF  DECISION": 3,
    "REASONS FOR D ECISION": 1,
    "PR ELIMINARY ISSUE": 1,
    "ISSUES A ND DECISION": 1,
    "I. DETERMINATION OF THE APPEAL": 1,
    "III.  SUBMISSIONS": 1,
    "IV.  STANDARD OF REVIEW": 1,
    "IV. REMEDIES": 1,
    "EASONS FOR DECISION AND ORDER": 1,
    "APPELANT  APPELLANT": 1,
    "CORAM  CORAM": 2,
    "IMMIGRATION AND REFUGEE": 1,
    "EASONS FOR DECISION AND ORDER  M": 1,
    "APPELLANT  APPELANT": 1,
    "DET ERMINATION": 3,
    "RESIDENC Y OBLIGATION": 1,
    "BACK ROUND": 1,
    "ABDOLMAJID ASHOORI": 1,
    "AMIR HOSSEI N ASHORI": 1,
    "INTRODUCTION AND ISSUES": 9,
    "VALIDITY OF RESIDENCY DECISION": 3,
    "SPECIAL RELIEF": 5,
    "HUMANITARIAN AND COM PASSIONATE CONSIDERA TIONS": 3,
    "STATE PROTECTION": 2,
    "REMOVA L ORDER": 1,
    "PRELIMINARY ISSUE": 2,
    "THE HEARING": 1,
    "WIDIAN ABOU -TABLE": 1,
    "REASO NS FOR DECISION": 1,
    "HITIWEDI.": 1,
    "REA SONS FOR DECISION": 2,
    "IMPORTANT WARNING": 1,
    "ISSUE AND DETERMINAT ION": 1,
    "ANALYSIS FACTORS": 1,
    "DETERMI NATION": 1,
    "IFA": 2,
    "ANALYS IS OF FACTORS": 1,
    "GURBAKSH KAUR PHAGURA": 1,
    "KASHMIR KAUR PHAGURA": 1,
    "XXXXXXXX PHAGURA": 1,
    "HUMANITARIAN AND COMPASSIONATE CONSIDERATIONS": 3,
    "MIN -JI KIM": 1,
    "SIEN JUNG YEH": 1,
    "BACK GROUND": 1,
    "APPLICATION": 6,
    "APPLICATION FOR AN O RAL HEARING16": 1,
    "SUPPORT YOUR CLAIM": 1,
    "EXCLUSION ORDER": 4,
    "PARAMJIT DOLON": 1,
    "APPLICATION TO VACATE": 2,
    "IN CAMERA  HUIS CLOS": 1,
    "MINISTER OF CITIZENSHIP AND IMMIGRATION": 1,
    "IN PRIVATE  HUIS CLOS": 167,
    "DEPARTURE ORDER": 1,
    "QI GEORGE LU": 1,
    "CHO-HUNG MA": 1,
    "BACKGROUN D": 3,
    "APPLICATION SPONSORSHIP": 1,
    "NOT ICE OF DECISION": 3,
    "STATUTOR Y PROVISIONS": 1,
    "BACKGROUND2": 1,
    "HSIU -M IAO YU C": 1,
    "HAO HUA CHEN": 1,
    "XXXXXXX NGUYEN": 1,
    "FC 349.": 1,
    "CORAM CORAM": 67,
    "SHAFFIRA SHAH": 1,
    "BACKGROUND  AND ALLEGATIONS": 1,
    "CLAIMANT": 3,
    "REASONS FOR DEC ISION": 1,
    "LEGISLATIVE PROVISIONS": 1,
    "NOTICE OF DECISION AND REASONS": 4,
    "GROUNDS OF  APPEAL AND REMEDY SOUGHT": 1,
    "IFA.": 2,
    "NOTICE OF DECIS ION": 1,
    "INTRODUCTION  REASONS FOR DECISION": 1,
    "NOTICE OF D ECISION": 1,
    "REASONS F OR DECISION": 1,
    "ISSUES AND DECISION": 3,
    "AIDA CADAUAN PO BIRD": 1,
    "XXXXX  2003.": 3,
    "GURDEV SINGH DHALIWAL": 1,
    "WAFAA MOUHINE TALEB": 1,
    "TA2--20647": 1,
    "ANA LYSIS": 1,
    "ANALYSIS AND FINDINGS OF FACT": 2,
    "HUMANITARIAN ANALYSIS": 1,
    "OLYMPIO VICTORIO CAPARAS": 1,
    "STATUTORY PROVISION S": 1,
    "NOTI CE OF DECISION": 2,
    "SEYED ALI MOUSAVI-NIKOU": 1,
    "XXXXX  2005.": 1,
    "XXXXXXXXXXXXX JAVIER CARLA MAE ARABIA": 1,
    "ISSUE AND DETERMINATION": 1,
    "RAVJIBHAI DHULABHAI BHOI": 1,
    "NOTIC E OF DECISION": 1,
    "HUMANIT ARIAN AND COMPASSIONATE CONSIDERATIONS": 1,
    "OVERVIE W": 1,
    "RESIDENCY OBLIGATIO N APPEAL": 1,
    "POST -HEARING DISCLOSURE": 1,
    "RUSSIA": 1,
    "STANDARD OF REVIEW": 10,
    "ANALY SIS": 3,
    "DE TERMINATIONS": 1,
    "SURNAME:    XXXXXXXXGIVEN NAMES:   XXXXXX": 1,
    "NOT ICE OF DEC ISION": 1,
    "KOSOVO": 1,
    "TB 7-16004                          4283 -6717": 1,
    "TB 7-16005                          4283 -6731": 1,
    "KUNTAL ROHITKUM  PATHAK": 1,
    "VENUS KUNTAL PATHAK": 1,
    "MISREPRESENTATIONS": 1,
    "CON TEXT": 1,
    "JURI SDICTION": 1,
    "IRPR.": 1,
    "REASONS FOR ORAL DECISION": 1,
    "DESIGNATIVE REPRESENTATIVE": 1,
    "BACHAR  IBRAHIM  YOUNES": 1,
    "SAMIRA  SAAD  THIFOUR": 1,
    "OMAROU  BACHAR  XXXXXX": 1,
    "RE SIDENCY OBLIGATION": 1,
    "REASON S FOR DECISION": 1,
    "APPEAL": 1,
    "EXTENT OF NON -COMPLIANCE": 1,
    "RETURN": 1,
    "FAMILY TIES": 1,
    "ESTABLISHMENT IN CANADA": 1,
    "POTENTIAL HARDSHIP TO THE APPELLANT": 1,
    "BEST INTERESTS OF THE CHILDREN": 1,
    "DISPOSITI ON": 1,
    "REMOVAL  ORDER": 1,
    "TREATM ENT OF THE EVIDENCE": 1,
    "DIS POSITION AND REMEDY": 1,
    "BACKGRO UND": 1,
    "CREDIBILITY FINDINGS": 1,
    "DISPOSITION AND REME DY": 3,
    "ISSUES TO BE DETERMINED": 1,
    "REVINA SANTIAGO RIMPOLA": 1,
    "BDP.": 1,
    "DETERMINATION  AND  ISSUES": 1,
    "EDWARD  J. SPADER": 1,
    "IDENTITY": 11,
    "NOT A GENUINE CHRISTIAN": 4,
    "CHRISTIAN RISK IN FUJIAN": 3,
    "CONCLUSION FOR THE CLAIMANT": 3,
    "CHILE": 3,
    "REPUBLIC": 1,
    "REAS ONS FOR DECISION": 1,
    "BACKGROUND AND ANALYSIS": 1,
    "THE STANDARD OF REVI EW": 1,
    "SUMMARY AND DETERMIN ATION": 1,
    "YAGHOUB  NASRI  SARAEI": 1,
    "ZARRINDOKHT POURNASROLLAH HAJI SARAEI": 1,
    "FACTUAL FINDINGS AND ANALYSIS": 1,
    "PARVINDER  SINGH  JHGRA": 1,
    "HEARING AND  SUBMISSIONS": 1,
    "RELEVANT LEGISLATION": 1,
    "LEGAL VALIDITY OF THE REFUSAL": 1,
    "SPAIN": 2,
    "DETERMINA TION": 2,
    "XXXXX  2007.": 2,
    "HEARING AND DISCLOSURE": 2,
    "CONFIDENTIAL": 2,
    "REMO VAL ORDER": 2,
    "MORTIMER BASIL DE SANTOS": 2,
    "NIL": 5,
    "CHI-FANG YEH Y": 2,
    "EH-FAN TIAU": 2,
    "FARIBA NAFARI": 2,
    "VIOLETA SPASSOVA-TUNANOVA": 2,
    "ISSUE  AND DECISION": 2,
    "PRINCIPAL CLAIMANT": 2,
    "AUC .": 1,
    "NIGERIA": 2,
    "ALL EGATIONS": 7,
    "BURUNDI": 1,
    "SUMMARY OF ALLEGED F ACTS": 1,
    "AN ALYSIS": 1,
    "THE SITUATION IN GUANGDONG PROVINCE": 1,
    "CHURCH": 1,
    "SUMMARY OF ALLEGED FACTS": 11,
    "IDE NTITY": 1,
    "CRE DIBILITY": 1,
    "FE AR": 1,
    "ALLEGATI ONS": 1,
    "COLOMBIA": 1,
    "IDENTITY DOCUMENTS  AND PRESENCE IN CHINA": 1,
    "RIC.": 1,
    "OTHER CREDIBILITY CONCERNS IN TESTIMONY": 1,
    "THE PSB SUMMONS": 1,
    "INTRODUCTIO N": 1,
    "ALLEGED FACTS": 6,
    "FCT 989.": 2,
    "VINCENT AND THE GRENADINES": 1,
    "CHINA": 2,
    "XXXXX  2010.": 1,
    "SRI LANKA": 1,
    "GUATEMALA": 2,
    "IDENTIT Y": 2,
    "SUMMARY OF AL LEGED FACTS": 1,
    "MEXICO": 1,
    "ORAL REASONS FOR DEC ISION": 1,
    "ALLE GATIONS": 2,
    "GRENADINES": 1,
    "CREDIBILITY CONCERNS": 1,
    "ANY ARREST WARRANT OR SUMMONS": 1,
    "RISK IN FUJIAN": 1,
    "FC 1274.": 1,
    "CR EDIBILIT Y": 1,
    "XXXXXX  2006.": 1,
    "XXXXX 2008.": 1,
    "FC 977.": 2,
    "RAL REASONS FOR DECISION  XXXXX XXXXX": 1,
    "ONCLUSION": 2,
    "PRAIDA": 1,
    "ANALYSIS:   IDENTITY:": 1,
    "FC 44.": 1,
    "ALL EGATIONS3": 1,
    "ORAL REASONS": 4,
    "HONDURAS": 1,
    "ONCURRED IN BY : XXXXXXXXXXXXXXX  M": 1,
    "ONCURRED IN BY : XXXXXXXXXXXXXXXXXX  M": 1,
    "XXXXX  2002.": 1,
    "XXXXX  2009.": 1,
    "CONCLUSION:": 1,
    "CORAM": 1,
    "MINISTERE DE L": 1,
    "MALE  CLAIMANT - XXXXXXXXX": 1,
    "ORAL DECISION AND REASONS": 1,
    "XXXXX  1989.": 2,
    "ANALYSIS I": 2,
    "CIRCUMSTANCES": 1,
    "ETERMINATION": 1,
    "CHN103401.E .": 1,
    "DEC ISION": 1,
    "JEGATHESWARY  SOORIYAKUMAR": 1,
    "RELEVE NT LAW": 1,
    "ANALYTICAL FRAMWOR K": 1,
    "DEPENDENT DAUGHTER": 1,
    "MARRIAGE": 1,
    "REASONS AND DECISI ON": 1,
    "REASONS AND DE CISION": 1,
    "DA FAN": 1,
    "SIN FUN PAPPER NG": 1,
    "MINH VIET LAM": 1,
    "WEN GUI LU": 1,
    "SERGEJ PESIC": 1,
    "GURDIP SINGH": 1,
    "ZHANG": 1,
    "IOAN VLAD": 1,
    "REAS ONS FOR D ECISION": 1,
    "OVERVIEW AND PROCEDURAL NOTES": 1,
    "ISSUE AND THE LAW": 1
  },
  "top_headers": {
    "NOTICE OF DECISION": 734,
    "REASONS FOR DECISION": 669,
    "CONCLUSION": 597,
    "ANALYSIS": 525,
    "BACKGROUND": 306,
    "DETERMINATION": 258,
    "DECISION": 251,
    "REMOVAL ORDER": 246,
    "INTRODUCTION": 212,
    "RESIDENCY OBLIGATION": 211,
    "SPONSORSHIP": 174,
    "IN PRIVATE  HUIS CLOS": 167,
    "OVERVIEW": 123,
    "ISSUE": 123,
    "ALLEGATIONS": 72,
    "CORAM CORAM": 67,
    "ORAL REASONS FOR DECISION": 52,
    "ROLE OF THE RAD": 51,
    "ISSUES": 39,
    "ANALYS IS": 32,
    "DISPOSITION": 30,
    "DETERMINATION OF THE APPEAL": 30,
    "ISSUES IN APPEAL": 24,
    "HEARING": 24,
    "LAW": 12,
    "IRPA .": 11,
    "AMENDED": 11,
    "IDENTITY": 11,
    "SUMMARY OF ALLEGED FACTS": 11,
    "ISSUE AND DECISION": 10,
    "MERITS OF THE APPEAL": 10,
    "SUBMISSIONS": 10,
    "IRPA.": 10,
    "I. INTRODUCTION": 10,
    "REASONS AND  DECISION": 10,
    "STANDARD OF REVIEW": 10,
    "II. BACKGROUND": 9,
    "REMOVAL ORDER APPEAL": 9,
    "INTRODUCTION AND ISSUES": 9,
    "CREDIBILITY": 8,
    "CONCLUSIO N": 8,
    "SUMMARY": 8,
    "NO NEW EVIDENCE OR ORAL HEARING": 8,
    "LEGAL VALIDITY": 8,
    "SPONSORSHIP APPEAL": 8,
    "ADMISSIBILITY OF EVIDENCE SUBMITTED ON APPEAL": 7,
    "NO ORAL HEARING": 7,
    "NEW EVIDENCE": 7,
    "TB 7-18394                           5969 -6878": 7,
    "ALL EGATIONS": 7,
    "III.  DETERMINATIVE ISSUE": 6,
    "RESIDENCY OBLIGATION APPEAL": 6,
    "HUMANITARIAN AND COM PASSIONATE GROUNDS": 6,
    "APPLICATION": 6,
    "ALLEGED FACTS": 6,
    "RAD ANALYSIS": 5,
    "CONC LUSION": 5,
    "NOTICE  OF DECISION": 5,
    "CONCLUS ION": 5,
    "RAD.": 5,
    "REMOVAL": 5,
    "SCOPE OF THE APPEAL": 5,
    "IMMIGRATION AND REFUGEE BOARD": 5,
    "HUMANITARIAN AND COMPASSIONATE GROUNDS": 5,
    "VI.  REMEDY": 5,
    "DECIS ION": 5,
    "REASONS FOR DECISIO N": 5,
    "EVIDENCE": 5,
    "NOTICE OF DE CISION": 5,
    "DETERMINATION OF THE APPLICATION": 5,
    "RPD.": 5,
    "SPECIAL RELIEF": 5,
    "NIL": 5,
    "EXPRESS STATUTORY CONDITIONS": 4,
    "DE CISION": 4,
    "CON CLUSION": 4,
    "DISPOSITION AND REMEDY": 4,
    "RELEVANT LAW": 4,
    "VII.  REMEDY": 4,
    "DE TERMINATION": 4,
    "V.  ANALYSI S": 4,
    "V. ANALYSIS": 4,
    "EXCLUSION ORDER": 4,
    "NOTICE OF DECISION AND REASONS": 4,
    "NOT A GENUINE CHRISTIAN": 4,
    "ORAL REASONS": 4,
    "REASONS AND DECISION": 3,
    "THE LAW": 3,
    "BACKGR OUND": 3,
    "INTRODUCTION AND ISSUE": 3,
    "CONTEXT": 3,
    "REASONS FOR DE CISION": 3,
    "SUBMISSIONS BY THE APPELLANT": 3,
    "REASONS FOR DECISI ON": 3,
    "ANALYSIS AND FINDING S OF FACT": 3,
    "ROLE OF RAD": 3,
    "PRELIMINARY MATTERS": 3,
    "BACKGROU ND": 3,
    "DETERMINAT ION": 3,
    "REASONS  FOR DECISION": 3
  },
  "key_header_stats": {
    "determination": {
      "DETERMINATION": 258,
      "DECISION": 251,
      "DISPOSITION": 30,
      "FINDINGS": 0
    },
    "conclusion": {
      "CONCLUSION": 597,
      "CONCLUSIONS": 0
    },
    "analysis": {
      "ANALYSIS": 525,
      "ASSESSMENT": 0,
      "REASONS": 0,
      "REASONS FOR DECISION": 669
    }
  }
}